{"metadata": {"dbt_schema_version": "https://schemas.getdbt.com/dbt/catalog/v1.json", "dbt_version": "1.11.11", "generated_at": "2026-06-01T17:06:37.627637Z", "invocation_id": "3b75fc3d-7dd8-4aea-9a80-b2d80099d12b", "invocation_started_at": "2026-06-01T17:06:35.317737Z", "env": {}}, "nodes": {"model.transform.fact_match": {"metadata": {"type": "BASE TABLE", "schema": "gold", "name": "fact_match", "database": "DataWarehouse", "comment": null, "owner": "dbo"}, "columns": {"id": {"type": "int", "index": 1, "name": "id", "comment": null}, "competition_id": {"type": "int", "index": 2, "name": "competition_id", "comment": null}, "season_id": {"type": "int", "index": 3, "name": "season_id", "comment": null}, "matchday": {"type": "int", "index": 4, "name": "matchday", "comment": null}, "home_team_id": {"type": "int", "index": 5, "name": "home_team_id", "comment": null}, "away_team_id": {"type": "int", "index": 6, "name": "away_team_id", "comment": null}, "utc_date": {"type": "datetime2", "index": 7, "name": "utc_date", "comment": null}, "status": {"type": "sysname", "index": 8, "name": "status", "comment": null}, "stage": {"type": "sysname", "index": 9, "name": "stage", "comment": null}, "group": {"type": "sysname", "index": 10, "name": "group", "comment": null}, "score_winner": {"type": "sysname", "index": 11, "name": "score_winner", "comment": null}, "score_duration": {"type": "sysname", "index": 12, "name": "score_duration", "comment": null}, "score_full_time_home": {"type": "int", "index": 13, "name": "score_full_time_home", "comment": null}, "score_full_time_away": {"type": "int", "index": 14, "name": "score_full_time_away", "comment": null}, "score_half_time_home": {"type": "int", "index": 15, "name": "score_half_time_home", "comment": null}, "score_half_time_away": {"type": "int", "index": 16, "name": "score_half_time_away", "comment": null}, "_updated_at": {"type": "datetime", "index": 17, "name": "_updated_at", "comment": null}}, "stats": {"has_stats": {"id": "has_stats", "label": "Has Stats?", "value": false, "include": false, "description": "Indicates whether there are statistics for this table"}}, "unique_id": "model.transform.fact_match"}, "model.transform.fact_match_team": {"metadata": {"type": "BASE TABLE", "schema": "gold", "name": "fact_match_team", "database": "DataWarehouse", "comment": null, "owner": "dbo"}, "columns": {"match_id": {"type": "int", "index": 1, "name": "match_id", "comment": null}, "competition_id": {"type": "int", "index": 2, "name": "competition_id", "comment": null}, "season_id": {"type": "int", "index": 3, "name": "season_id", "comment": null}, "matchday": {"type": "int", "index": 4, "name": "matchday", "comment": null}, "utc_date": {"type": "datetime2", "index": 5, "name": "utc_date", "comment": null}, "team_id": {"type": "int", "index": 6, "name": "team_id", "comment": null}, "is_home": {"type": "int", "index": 7, "name": "is_home", "comment": null}, "goals_scored_half_time": {"type": "int", "index": 8, "name": "goals_scored_half_time", "comment": null}, "goals_conceded_half_time": {"type": "int", "index": 9, "name": "goals_conceded_half_time", "comment": null}, "goals_scored_full_time": {"type": "int", "index": 10, "name": "goals_scored_full_time", "comment": null}, "goals_conceded_full_time": {"type": "int", "index": 11, "name": "goals_conceded_full_time", "comment": null}, "points": {"type": "int", "index": 12, "name": "points", "comment": null}, "_updated_at": {"type": "datetime", "index": 13, "name": "_updated_at", "comment": null}}, "stats": {"has_stats": {"id": "has_stats", "label": "Has Stats?", "value": false, "include": false, "description": "Indicates whether there are statistics for this table"}}, "unique_id": "model.transform.fact_match_team"}, "model.transform.dim_competition": {"metadata": {"type": "BASE TABLE", "schema": "gold", "name": "dim_competition", "database": "DataWarehouse", "comment": null, "owner": "dbo"}, "columns": {"id": {"type": "int", "index": 1, "name": "id", "comment": null}, "name": {"type": "sysname", "index": 2, "name": "name", "comment": null}, "code": {"type": "sysname", "index": 3, "name": "code", "comment": null}, "type": {"type": "sysname", "index": 4, "name": "type", "comment": null}, "emblem": {"type": "sysname", "index": 5, "name": "emblem", "comment": null}, "area_id": {"type": "int", "index": 6, "name": "area_id", "comment": null}, "_updated_at": {"type": "datetime", "index": 7, "name": "_updated_at", "comment": null}}, "stats": {"has_stats": {"id": "has_stats", "label": "Has Stats?", "value": false, "include": false, "description": "Indicates whether there are statistics for this table"}}, "unique_id": "model.transform.dim_competition"}, "model.transform.dim_season": {"metadata": {"type": "BASE TABLE", "schema": "gold", "name": "dim_season", "database": "DataWarehouse", "comment": null, "owner": "dbo"}, "columns": {"season_id": {"type": "int", "index": 1, "name": "season_id", "comment": null}, "season_start_date": {"type": "date", "index": 2, "name": "season_start_date", "comment": null}, "season_end_date": {"type": "date", "index": 3, "name": "season_end_date", "comment": null}, "season_label": {"type": "sysname", "index": 4, "name": "season_label", "comment": null}}, "stats": {"has_stats": {"id": "has_stats", "label": "Has Stats?", "value": false, "include": false, "description": "Indicates whether there are statistics for this table"}}, "unique_id": "model.transform.dim_season"}, "seed.transform.dim_date": {"metadata": {"type": "BASE TABLE", "schema": "gold", "name": "dim_date", "database": "DataWarehouse", "comment": null, "owner": "dbo"}, "columns": {"date": {"type": "date", "index": 1, "name": "date", "comment": null}, "date_uk": {"type": "varchar", "index": 2, "name": "date_uk", "comment": null}, "day_of_month": {"type": "int", "index": 3, "name": "day_of_month", "comment": null}, "day_name": {"type": "varchar", "index": 4, "name": "day_name", "comment": null}, "month_number": {"type": "int", "index": 5, "name": "month_number", "comment": null}, "month_name": {"type": "varchar", "index": 6, "name": "month_name", "comment": null}, "year": {"type": "int", "index": 7, "name": "year", "comment": null}, "end_of_month": {"type": "date", "index": 8, "name": "end_of_month", "comment": null}, "is_weekend": {"type": "int", "index": 9, "name": "is_weekend", "comment": null}}, "stats": {"has_stats": {"id": "has_stats", "label": "Has Stats?", "value": false, "include": false, "description": "Indicates whether there are statistics for this table"}}, "unique_id": "seed.transform.dim_date"}, "model.transform.matches": {"metadata": {"type": "BASE TABLE", "schema": "silver", "name": "matches", "database": "DataWarehouse", "comment": null, "owner": "dbo"}, "columns": {"id": {"type": "int", "index": 1, "name": "id", "comment": null}, "competition_id": {"type": "int", "index": 2, "name": "competition_id", "comment": null}, "season_id": {"type": "int", "index": 3, "name": "season_id", "comment": null}, "matchday": {"type": "int", "index": 4, "name": "matchday", "comment": null}, "home_team_id": {"type": "int", "index": 5, "name": "home_team_id", "comment": null}, "away_team_id": {"type": "int", "index": 6, "name": "away_team_id", "comment": null}, "utc_date": {"type": "datetime2", "index": 7, "name": "utc_date", "comment": null}, "status": {"type": "sysname", "index": 8, "name": "status", "comment": null}, "stage": {"type": "sysname", "index": 9, "name": "stage", "comment": null}, "group": {"type": "sysname", "index": 10, "name": "group", "comment": null}, "score_winner": {"type": "sysname", "index": 11, "name": "score_winner", "comment": null}, "score_duration": {"type": "sysname", "index": 12, "name": "score_duration", "comment": null}, "score_full_time_home": {"type": "int", "index": 13, "name": "score_full_time_home", "comment": null}, "score_full_time_away": {"type": "int", "index": 14, "name": "score_full_time_away", "comment": null}, "score_half_time_home": {"type": "int", "index": 15, "name": "score_half_time_home", "comment": null}, "score_half_time_away": {"type": "int", "index": 16, "name": "score_half_time_away", "comment": null}, "_updated_at": {"type": "datetime", "index": 17, "name": "_updated_at", "comment": null}}, "stats": {"has_stats": {"id": "has_stats", "label": "Has Stats?", "value": false, "include": false, "description": "Indicates whether there are statistics for this table"}}, "unique_id": "model.transform.matches"}, "model.transform.dim_team": {"metadata": {"type": "BASE TABLE", "schema": "gold", "name": "dim_team", "database": "DataWarehouse", "comment": null, "owner": "dbo"}, "columns": {"team_id": {"type": "int", "index": 1, "name": "team_id", "comment": null}, "team_name": {"type": "sysname", "index": 2, "name": "team_name", "comment": null}, "team_tla": {"type": "sysname", "index": 3, "name": "team_tla", "comment": null}, "team_short_name": {"type": "sysname", "index": 4, "name": "team_short_name", "comment": null}, "team_crest": {"type": "sysname", "index": 5, "name": "team_crest", "comment": null}}, "stats": {"has_stats": {"id": "has_stats", "label": "Has Stats?", "value": false, "include": false, "description": "Indicates whether there are statistics for this table"}}, "unique_id": "model.transform.dim_team"}, "model.transform.competitions": {"metadata": {"type": "BASE TABLE", "schema": "silver", "name": "competitions", "database": "DataWarehouse", "comment": null, "owner": "dbo"}, "columns": {"id": {"type": "int", "index": 1, "name": "id", "comment": null}, "name": {"type": "sysname", "index": 2, "name": "name", "comment": null}, "code": {"type": "sysname", "index": 3, "name": "code", "comment": null}, "type": {"type": "sysname", "index": 4, "name": "type", "comment": null}, "emblem": {"type": "sysname", "index": 5, "name": "emblem", "comment": null}, "area_id": {"type": "int", "index": 6, "name": "area_id", "comment": null}, "_updated_at": {"type": "datetime", "index": 7, "name": "_updated_at", "comment": null}}, "stats": {"has_stats": {"id": "has_stats", "label": "Has Stats?", "value": false, "include": false, "description": "Indicates whether there are statistics for this table"}}, "unique_id": "model.transform.competitions"}, "model.transform.seasons": {"metadata": {"type": "BASE TABLE", "schema": "silver", "name": "seasons", "database": "DataWarehouse", "comment": null, "owner": "dbo"}, "columns": {"season_id": {"type": "int", "index": 1, "name": "season_id", "comment": null}, "season_start_date": {"type": "date", "index": 2, "name": "season_start_date", "comment": null}, "season_end_date": {"type": "date", "index": 3, "name": "season_end_date", "comment": null}, "season_label": {"type": "sysname", "index": 4, "name": "season_label", "comment": null}}, "stats": {"has_stats": {"id": "has_stats", "label": "Has Stats?", "value": false, "include": false, "description": "Indicates whether there are statistics for this table"}}, "unique_id": "model.transform.seasons"}, "model.transform.teams": {"metadata": {"type": "BASE TABLE", "schema": "silver", "name": "teams", "database": "DataWarehouse", "comment": null, "owner": "dbo"}, "columns": {"team_id": {"type": "int", "index": 1, "name": "team_id", "comment": null}, "team_name": {"type": "sysname", "index": 2, "name": "team_name", "comment": null}, "team_tla": {"type": "sysname", "index": 3, "name": "team_tla", "comment": null}, "team_short_name": {"type": "sysname", "index": 4, "name": "team_short_name", "comment": null}, "team_crest": {"type": "sysname", "index": 5, "name": "team_crest", "comment": null}}, "stats": {"has_stats": {"id": "has_stats", "label": "Has Stats?", "value": false, "include": false, "description": "Indicates whether there are statistics for this table"}}, "unique_id": "model.transform.teams"}, "model.transform.areas": {"metadata": {"type": "BASE TABLE", "schema": "silver", "name": "areas", "database": "DataWarehouse", "comment": null, "owner": "dbo"}, "columns": {"area_id": {"type": "int", "index": 1, "name": "area_id", "comment": null}, "area_name": {"type": "sysname", "index": 2, "name": "area_name", "comment": null}}, "stats": {"has_stats": {"id": "has_stats", "label": "Has Stats?", "value": false, "include": false, "description": "Indicates whether there are statistics for this table"}}, "unique_id": "model.transform.areas"}, "model.transform.vw_season_summary": {"metadata": {"type": "VIEW", "schema": "gold", "name": "vw_season_summary", "database": "DataWarehouse", "comment": null, "owner": "dbo"}, "columns": {"team_id": {"type": "int", "index": 1, "name": "team_id", "comment": null}, "team_name": {"type": "sysname", "index": 2, "name": "team_name", "comment": null}, "season_label": {"type": "sysname", "index": 3, "name": "season_label", "comment": null}, "competition": {"type": "sysname", "index": 4, "name": "competition", "comment": null}, "games_played": {"type": "int", "index": 5, "name": "games_played", "comment": null}, "games_won": {"type": "int", "index": 6, "name": "games_won", "comment": null}, "games_lost": {"type": "int", "index": 7, "name": "games_lost", "comment": null}, "games_drawn": {"type": "int", "index": 8, "name": "games_drawn", "comment": null}, "goals_scored": {"type": "int", "index": 9, "name": "goals_scored", "comment": null}, "goals_conceded": {"type": "int", "index": 10, "name": "goals_conceded", "comment": null}, "goal_difference": {"type": "int", "index": 11, "name": "goal_difference", "comment": null}, "clean_sheets": {"type": "int", "index": 12, "name": "clean_sheets", "comment": null}, "total_points": {"type": "int", "index": 13, "name": "total_points", "comment": null}, "points_per_game": {"type": "numeric", "index": 14, "name": "points_per_game", "comment": null}, "home_games_played": {"type": "int", "index": 15, "name": "home_games_played", "comment": null}, "home_games_won": {"type": "int", "index": 16, "name": "home_games_won", "comment": null}, "home_games_lost": {"type": "int", "index": 17, "name": "home_games_lost", "comment": null}, "home_games_drawn": {"type": "int", "index": 18, "name": "home_games_drawn", "comment": null}, "home_goals_scored": {"type": "int", "index": 19, "name": "home_goals_scored", "comment": null}, "home_goals_conceded": {"type": "int", "index": 20, "name": "home_goals_conceded", "comment": null}, "home_goal_difference": {"type": "int", "index": 21, "name": "home_goal_difference", "comment": null}, "home_clean_sheets": {"type": "int", "index": 22, "name": "home_clean_sheets", "comment": null}, "home_total_points": {"type": "int", "index": 23, "name": "home_total_points", "comment": null}, "home_points_per_game": {"type": "numeric", "index": 24, "name": "home_points_per_game", "comment": null}, "away_games_played": {"type": "int", "index": 25, "name": "away_games_played", "comment": null}, "away_games_won": {"type": "int", "index": 26, "name": "away_games_won", "comment": null}, "away_games_lost": {"type": "int", "index": 27, "name": "away_games_lost", "comment": null}, "away_games_drawn": {"type": "int", "index": 28, "name": "away_games_drawn", "comment": null}, "away_goals_scored": {"type": "int", "index": 29, "name": "away_goals_scored", "comment": null}, "away_goals_conceded": {"type": "int", "index": 30, "name": "away_goals_conceded", "comment": null}, "away_goal_difference": {"type": "int", "index": 31, "name": "away_goal_difference", "comment": null}, "away_clean_sheets": {"type": "int", "index": 32, "name": "away_clean_sheets", "comment": null}, "away_total_points": {"type": "int", "index": 33, "name": "away_total_points", "comment": null}, "away_points_per_game": {"type": "numeric", "index": 34, "name": "away_points_per_game", "comment": null}}, "stats": {"has_stats": {"id": "has_stats", "label": "Has Stats?", "value": false, "include": false, "description": "Indicates whether there are statistics for this table"}}, "unique_id": "model.transform.vw_season_summary"}, "model.transform.vw_match_results": {"metadata": {"type": "VIEW", "schema": "gold", "name": "vw_match_results", "database": "DataWarehouse", "comment": null, "owner": "dbo"}, "columns": {"season": {"type": "sysname", "index": 1, "name": "season", "comment": null}, "competition": {"type": "sysname", "index": 2, "name": "competition", "comment": null}, "matchday": {"type": "int", "index": 3, "name": "matchday", "comment": null}, "match_date": {"type": "sysname", "index": 4, "name": "match_date", "comment": null}, "match": {"type": "sysname", "index": 5, "name": "match", "comment": null}, "half_time_score": {"type": "sysname", "index": 6, "name": "half_time_score", "comment": null}, "full_time_score": {"type": "sysname", "index": 7, "name": "full_time_score", "comment": null}, "result": {"type": "varchar", "index": 8, "name": "result", "comment": null}}, "stats": {"has_stats": {"id": "has_stats", "label": "Has Stats?", "value": false, "include": false, "description": "Indicates whether there are statistics for this table"}}, "unique_id": "model.transform.vw_match_results"}, "model.transform.vw_team_form": {"metadata": {"type": "VIEW", "schema": "gold", "name": "vw_team_form", "database": "DataWarehouse", "comment": null, "owner": "dbo"}, "columns": {"team_name": {"type": "sysname", "index": 1, "name": "team_name", "comment": null}, "match_date": {"type": "datetime2", "index": 2, "name": "match_date", "comment": null}, "competition": {"type": "sysname", "index": 3, "name": "competition", "comment": null}, "matchday": {"type": "int", "index": 4, "name": "matchday", "comment": null}, "home_or_away": {"type": "varchar", "index": 5, "name": "home_or_away", "comment": null}, "opponent_name": {"type": "sysname", "index": 6, "name": "opponent_name", "comment": null}, "goals_scored": {"type": "int", "index": 7, "name": "goals_scored", "comment": null}, "goals_conceded": {"type": "int", "index": 8, "name": "goals_conceded", "comment": null}, "result": {"type": "varchar", "index": 9, "name": "result", "comment": null}, "points": {"type": "int", "index": 10, "name": "points", "comment": null}, "last_5_rank": {"type": "bigint", "index": 11, "name": "last_5_rank", "comment": null}}, "stats": {"has_stats": {"id": "has_stats", "label": "Has Stats?", "value": false, "include": false, "description": "Indicates whether there are statistics for this table"}}, "unique_id": "model.transform.vw_team_form"}, "model.transform.vw_head_to_head": {"metadata": {"type": "VIEW", "schema": "gold", "name": "vw_head_to_head", "database": "DataWarehouse", "comment": null, "owner": "dbo"}, "columns": {"team_a_name": {"type": "sysname", "index": 1, "name": "team_a_name", "comment": null}, "team_b_name": {"type": "sysname", "index": 2, "name": "team_b_name", "comment": null}, "total_meetings": {"type": "int", "index": 3, "name": "total_meetings", "comment": null}, "team_a_goals": {"type": "int", "index": 4, "name": "team_a_goals", "comment": null}, "team_b_goals": {"type": "int", "index": 5, "name": "team_b_goals", "comment": null}, "team_a_wins": {"type": "int", "index": 6, "name": "team_a_wins", "comment": null}, "team_b_wins": {"type": "int", "index": 7, "name": "team_b_wins", "comment": null}, "draws": {"type": "int", "index": 8, "name": "draws", "comment": null}}, "stats": {"has_stats": {"id": "has_stats", "label": "Has Stats?", "value": false, "include": false, "description": "Indicates whether there are statistics for this table"}}, "unique_id": "model.transform.vw_head_to_head"}, "model.transform.vw_league_table": {"metadata": {"type": "VIEW", "schema": "gold", "name": "vw_league_table", "database": "DataWarehouse", "comment": null, "owner": "dbo"}, "columns": {"competition": {"type": "sysname", "index": 1, "name": "competition", "comment": null}, "matchday": {"type": "int", "index": 2, "name": "matchday", "comment": null}, "position": {"type": "bigint", "index": 3, "name": "position", "comment": null}, "team_name": {"type": "sysname", "index": 4, "name": "team_name", "comment": null}, "P": {"type": "int", "index": 5, "name": "P", "comment": null}, "W": {"type": "int", "index": 6, "name": "W", "comment": null}, "D": {"type": "int", "index": 7, "name": "D", "comment": null}, "L": {"type": "int", "index": 8, "name": "L", "comment": null}, "GF": {"type": "int", "index": 9, "name": "GF", "comment": null}, "GA": {"type": "int", "index": 10, "name": "GA", "comment": null}, "GD": {"type": "int", "index": 11, "name": "GD", "comment": null}, "Pts": {"type": "int", "index": 12, "name": "Pts", "comment": null}}, "stats": {"has_stats": {"id": "has_stats", "label": "Has Stats?", "value": false, "include": false, "description": "Indicates whether there are statistics for this table"}}, "unique_id": "model.transform.vw_league_table"}}, "sources": {"source.transform.bronze.matches": {"metadata": {"type": "BASE TABLE", "schema": "bronze", "name": "matches", "database": "DataWarehouse", "comment": null, "owner": "dbo"}, "columns": {"id": {"type": "int", "index": 1, "name": "id", "comment": null}, "competition_id": {"type": "int", "index": 2, "name": "competition_id", "comment": null}, "season_id": {"type": "int", "index": 3, "name": "season_id", "comment": null}, "season_start_date": {"type": "date", "index": 4, "name": "season_start_date", "comment": null}, "season_end_date": {"type": "date", "index": 5, "name": "season_end_date", "comment": null}, "matchday": {"type": "int", "index": 6, "name": "matchday", "comment": null}, "home_team_id": {"type": "int", "index": 7, "name": "home_team_id", "comment": null}, "home_team_name": {"type": "sysname", "index": 8, "name": "home_team_name", "comment": null}, "home_team_short_name": {"type": "sysname", "index": 9, "name": "home_team_short_name", "comment": null}, "home_team_tla": {"type": "sysname", "index": 10, "name": "home_team_tla", "comment": null}, "home_team_crest": {"type": "sysname", "index": 11, "name": "home_team_crest", "comment": null}, "away_team_id": {"type": "int", "index": 12, "name": "away_team_id", "comment": null}, "away_team_name": {"type": "sysname", "index": 13, "name": "away_team_name", "comment": null}, "away_team_short_name": {"type": "sysname", "index": 14, "name": "away_team_short_name", "comment": null}, "away_team_tla": {"type": "sysname", "index": 15, "name": "away_team_tla", "comment": null}, "away_team_crest": {"type": "sysname", "index": 16, "name": "away_team_crest", "comment": null}, "utc_date": {"type": "datetime2", "index": 17, "name": "utc_date", "comment": null}, "status": {"type": "sysname", "index": 18, "name": "status", "comment": null}, "stage": {"type": "sysname", "index": 19, "name": "stage", "comment": null}, "group": {"type": "sysname", "index": 20, "name": "group", "comment": null}, "score_winner": {"type": "sysname", "index": 21, "name": "score_winner", "comment": null}, "score_duration": {"type": "sysname", "index": 22, "name": "score_duration", "comment": null}, "score_full_time_home": {"type": "int", "index": 23, "name": "score_full_time_home", "comment": null}, "score_full_time_away": {"type": "int", "index": 24, "name": "score_full_time_away", "comment": null}, "score_half_time_home": {"type": "int", "index": 25, "name": "score_half_time_home", "comment": null}, "score_half_time_away": {"type": "int", "index": 26, "name": "score_half_time_away", "comment": null}, "_ingested_at": {"type": "datetime2", "index": 27, "name": "_ingested_at", "comment": null}, "_last_updated": {"type": "datetime2", "index": 28, "name": "_last_updated", "comment": null}}, "stats": {"has_stats": {"id": "has_stats", "label": "Has Stats?", "value": false, "include": false, "description": "Indicates whether there are statistics for this table"}}, "unique_id": "source.transform.bronze.matches"}, "source.transform.bronze.competitions": {"metadata": {"type": "BASE TABLE", "schema": "bronze", "name": "competitions", "database": "DataWarehouse", "comment": null, "owner": "dbo"}, "columns": {"id": {"type": "int", "index": 1, "name": "id", "comment": null}, "name": {"type": "sysname", "index": 2, "name": "name", "comment": null}, "code": {"type": "sysname", "index": 3, "name": "code", "comment": null}, "type": {"type": "sysname", "index": 4, "name": "type", "comment": null}, "emblem": {"type": "sysname", "index": 5, "name": "emblem", "comment": null}, "area_id": {"type": "int", "index": 6, "name": "area_id", "comment": null}, "area_name": {"type": "sysname", "index": 7, "name": "area_name", "comment": null}, "_ingested_at": {"type": "datetime2", "index": 8, "name": "_ingested_at", "comment": null}}, "stats": {"has_stats": {"id": "has_stats", "label": "Has Stats?", "value": false, "include": false, "description": "Indicates whether there are statistics for this table"}}, "unique_id": "source.transform.bronze.competitions"}}, "errors": null}